survivor/__init__.py
survivor-0.0.1.dist-info/DESCRIPTION.rst
survivor-0.0.1.dist-info/METADATA
survivor-0.0.1.dist-info/RECORD
survivor-0.0.1.dist-info/WHEEL
survivor-0.0.1.dist-info/metadata.json
survivor-0.0.1.dist-info/top_level.txt
