Metadata-Version: 2.0
Name: survivor
Version: 0.0.1
Summary: Toolkit for survival analysis on patient data
Home-page: https://github.com/n-s-f/survivor
Author: UNKNOWN
Author-email: UNKNOWN
License: UNKNOWN
Platform: UNKNOWN
